ACOCrawler/__init__.py
ACOCrawler/acocrawler.py
ACOCrawler/cli.py
ACOCrawler/crawler.py
ACOCrawler/components/__init__.py
ACOCrawler/components/aconeo4J.py
ACOCrawler/components/google.py
ACOCrawler/components/neo4J.py
ACOCrawler/components/node.py
ACOCrawler/components/score.py
ACOCrawler/components/scrape.py
ACOCrawler/components/url.py
ACOCrawler/components/wakati.py
ACOCrawler-0.2.0.dist-info/METADATA
ACOCrawler-0.2.0.dist-info/WHEEL
ACOCrawler-0.2.0.dist-info/entry_points.txt
ACOCrawler-0.2.0.dist-info/top_level.txt
ACOCrawler-0.2.0.dist-info/RECORD
